nsgvalidation.py
nsgvalidation-0.4.dist-info/LICENSE
nsgvalidation-0.4.dist-info/METADATA
nsgvalidation-0.4.dist-info/WHEEL
nsgvalidation-0.4.dist-info/top_level.txt
nsgvalidation-0.4.dist-info/RECORD
